syntax_parser_skeleton/__init__.py
syntax_parser_skeleton/baseobjects.py
syntax_parser_skeleton/example.py
syntax_parser_skeleton/visualisation.py
syntax_parser_skeleton/derivatives/__init__.py
syntax_parser_skeleton/derivatives/simpleregex.py
syntax_parser_skeleton/derivatives/singleregex.py
syntax_parser_skeleton-1.4.dist-info/LICENSE
syntax_parser_skeleton-1.4.dist-info/METADATA
syntax_parser_skeleton-1.4.dist-info/WHEEL
syntax_parser_skeleton-1.4.dist-info/top_level.txt
syntax_parser_skeleton-1.4.dist-info/RECORD
