Metadata-Version: 2.2
Name: syntax-parser-skeleton
Version: 1.4
Summary: skeleton of a sytaxparser
Author-email: "Adrian F. Hoefflin" <srccircumflex@outlook.com>
License: MIT License
Project-URL: Homepage, https://github.com/srccircumflex/syntax-parser-skeleton
Keywords: syntax,parser,skeleton,compiler,framework
Classifier: Topic :: Text Processing
Classifier: Topic :: Software Development :: Libraries :: Application Frameworks
Classifier: Topic :: Software Development :: Interpreters
Classifier: Topic :: Software Development :: Compilers
Classifier: Topic :: Software Development
Classifier: Programming Language :: Python
License-File: LICENSE
Provides-Extra: visualisation
Requires-Dist: dash; extra == "visualisation"
Requires-Dist: dash-cytoscape; extra == "visualisation"
